DrissionRecord/__init__.py
DrissionRecord/base.py
DrissionRecord/base.pyi
DrissionRecord/byte_recorder.py
DrissionRecord/byte_recorder.pyi
DrissionRecord/cell_style.py
DrissionRecord/cell_style.pyi
DrissionRecord/db_recorder.py
DrissionRecord/db_recorder.pyi
DrissionRecord/recorder.py
DrissionRecord/recorder.pyi
DrissionRecord/setter.py
DrissionRecord/setter.pyi
DrissionRecord/tools.py
DrissionRecord/tools.pyi
drissionrecord-1.1.0.dist-info/licenses/LICENSE
drissionrecord-1.1.0.dist-info/METADATA
drissionrecord-1.1.0.dist-info/WHEEL
drissionrecord-1.1.0.dist-info/top_level.txt
drissionrecord-1.1.0.dist-info/RECORD
