Metadata-Version: 2.4
Name: DrissionRecord
Version: 1.1.0
Summary: 用于记录数据的模块。
Home-page: https://gitcode.com/g1879/DrissionRecord
Author: g1879
Author-email: g1879@qq.com
License: MIT
Keywords: DrissionRecord
Classifier: Programming Language :: Python :: 3.6
Classifier: Development Status :: 4 - Beta
Classifier: Topic :: Utilities
Classifier: License :: OSI Approved :: BSD License
Requires-Python: >=3.6
License-File: LICENSE
Requires-Dist: openpyxl
Dynamic: author
Dynamic: author-email
Dynamic: classifier
Dynamic: description
Dynamic: description-content-type
Dynamic: home-page
Dynamic: keywords
Dynamic: license
Dynamic: license-file
Dynamic: requires-dist
Dynamic: requires-python
Dynamic: summary
